wwwpy/__init__.py
wwwpy/_build_meta.py
wwwpy/base_conf.py
wwwpy/bootstrap.py
wwwpy/exceptions.py
wwwpy/http.py
wwwpy/resources.py
wwwpy/rpc.py
wwwpy/unasync.py
wwwpy/webserver.py
wwwpy/websocket.py
wwwpy/asgi/__init__.py
wwwpy/asgi/echo_handler.py
wwwpy/asgi/favicon.txt
wwwpy/asgi/main_daphne.py
wwwpy/asgi/main_granian.py
wwwpy/asgi/main_hypercorn.py
wwwpy/asgi/main_tornado.py
wwwpy/asgi/main_uvicorn.py
wwwpy/asgi/tornado_asgi_handler.py
wwwpy/common/__init__.py
wwwpy/common/_raise_on_any.py
wwwpy/common/asynclib.py
wwwpy/common/attr_lib.py
wwwpy/common/collectionlib.py
wwwpy/common/detect.py
wwwpy/common/escapelib.py
wwwpy/common/event_observer.py
wwwpy/common/eventbus.py
wwwpy/common/exitlib.py
wwwpy/common/extension_point.py
wwwpy/common/fetch.py
wwwpy/common/fetch_debug.py
wwwpy/common/files.py
wwwpy/common/http_transport.py
wwwpy/common/indent.py
wwwpy/common/injectorlib.py
wwwpy/common/iterlib.py
wwwpy/common/loglib.py
wwwpy/common/modlib.py
wwwpy/common/property_monitor.py
wwwpy/common/reloader.py
wwwpy/common/result.py
wwwpy/common/settingslib.py
wwwpy/common/state.py
wwwpy/common/strings.py
wwwpy/common/time_logger.py
wwwpy/common/tree.py
wwwpy/common/type_listener.py
wwwpy/common/databind/__init__.py
wwwpy/common/databind/databind.py
wwwpy/common/designer/__init__.py
wwwpy/common/designer/canvas_selection.py
wwwpy/common/designer/class_path.py
wwwpy/common/designer/code_edit.py
wwwpy/common/designer/code_info.py
wwwpy/common/designer/code_strings.py
wwwpy/common/designer/comp_info.py
wwwpy/common/designer/el_common.py
wwwpy/common/designer/el_shoelace.json
wwwpy/common/designer/el_shoelace.py
wwwpy/common/designer/el_standard.py
wwwpy/common/designer/element_editor.py
wwwpy/common/designer/element_library.py
wwwpy/common/designer/html_edit.py
wwwpy/common/designer/html_locator.py
wwwpy/common/designer/html_parser.py
wwwpy/common/designer/html_parser_mod.py
wwwpy/common/designer/locator_lib.py
wwwpy/common/designer/log_emit.py
wwwpy-0.1.86.dist-info/licenses/LICENSE
wwwpy-0.1.86.dist-info/METADATA
wwwpy-0.1.86.dist-info/WHEEL
wwwpy-0.1.86.dist-info/entry_points.txt
wwwpy-0.1.86.dist-info/top_level.txt
wwwpy-0.1.86.dist-info/RECORD
