Metadata-Version: 2.4
Name: wwwpy
Version: 0.1.86
Summary: Build Powerful Web Applications: Simple, Scalable, and Fully Customizable
Author-email: Simone Giacomelli <simone.giacomelli@gmail.com>
License:                                  Apache License
Project-URL: Homepage, https://github.com/wwwpy-labs/wwwpy
Project-URL: Issues, https://github.com/wwwpy-labs/wwwpy/issues
Keywords: wwwpy,wasm,pyodide,web,development,dom,html,javascript
Classifier: Development Status :: 3 - Alpha
Classifier: Intended Audience :: Developers
Classifier: Operating System :: OS Independent
Classifier: Programming Language :: Python
Classifier: Programming Language :: Python :: 3 :: Only
Classifier: Programming Language :: Python :: 3
Classifier: Programming Language :: Python :: 3.10
Classifier: Programming Language :: Python :: 3.11
Classifier: Programming Language :: Python :: 3.12
Classifier: Programming Language :: Python :: 3.13
Classifier: Topic :: Software Development :: Build Tools
Classifier: Environment :: Web Environment
Requires-Python: >=3.10
License-File: LICENSE
Requires-Dist: tornado==6.4.2
Requires-Dist: watchdog==6.0.0
Requires-Dist: webtypy
Provides-Extra: test
Requires-Dist: tox; extra == "test"
Requires-Dist: pytest; extra == "test"
Requires-Dist: pytest-asyncio; extra == "test"
Requires-Dist: playwright; extra == "test"
Requires-Dist: pytest-playwright; extra == "test"
Requires-Dist: pytest-xvirt; extra == "test"
Requires-Dist: libcst==1.6.0; extra == "test"
Requires-Dist: rope==1.13.0; extra == "test"
Provides-Extra: dev
Requires-Dist: webtypy; extra == "dev"
Requires-Dist: playwright; extra == "dev"
Requires-Dist: setuptools; extra == "dev"
Requires-Dist: pytest-asyncio; extra == "dev"
Provides-Extra: pypi
Requires-Dist: twine; extra == "pypi"
Requires-Dist: build; extra == "pypi"
Provides-Extra: stubs
Requires-Dist: pyodide-stubs; extra == "stubs"
Provides-Extra: all
Requires-Dist: wwwpy[dev,pypi,stubs,test]; extra == "all"
Dynamic: license-file
